{
  "version": "6",
  "dialect": "sqlite",
  "tables": {
    "users_roles": {
      "name": "users_roles",
      "columns": {
        "order": {
          "name": "order",
          "type": "integer",
          "primaryKey": false,
          "notNull": true,
          "autoincrement": false
        },
        "parent_id": {
          "name": "parent_id",
          "type": "integer",
          "primaryKey": false,
          "notNull": true,
          "autoincrement": false
        },
        "value": {
          "name": "value",
          "type": "text",
          "primaryKey": false,
          "notNull": false,
          "autoincrement": false
        },
        "id": {
          "name": "id",
          "type": "integer",
          "primaryKey": true,
          "notNull": true,
          "autoincrement": false
        }
      },
      "indexes": {
        "users_roles_order_idx": {
          "name": "users_roles_order_idx",
          "columns": [
            "order"
          ],
          "isUnique": false
        },
        "users_roles_parent_idx": {
          "name": "users_roles_parent_idx",
          "columns": [
            "parent_id"
          ],
          "isUnique": false
        }
      },
      "foreignKeys": {
        "users_roles_parent_fk": {
          "name": "users_roles_parent_fk",
          "tableFrom": "users_roles",
          "tableTo": "users",
          "columnsFrom": [
            "parent_id"
          ],
          "columnsTo": [
            "id"
          ],
          "onDelete": "cascade",
          "onUpdate": "no action"
        }
      },
      "compositePrimaryKeys": {},
      "uniqueConstraints": {},
      "checkConstraints": {}
    },
    "users_sessions": {
      "name": "users_sessions",
      "columns": {
        "_order": {
          "name": "_order",
          "type": "integer",
          "primaryKey": false,
          "notNull": true,
          "autoincrement": false
        },
        "_parent_id": {
          "name": "_parent_id",
          "type": "integer",
          "primaryKey": false,
          "notNull": true,
          "autoincrement": false
        },
        "id": {
          "name": "id",
          "type": "text",
          "primaryKey": true,
          "notNull": true,
          "autoincrement": false
        },
        "created_at": {
          "name": "created_at",
          "type": "text",
          "primaryKey": false,
          "notNull": false,
          "autoincrement": false
        },
        "expires_at": {
          "name": "expires_at",
          "type": "text",
          "primaryKey": false,
          "notNull": true,
          "autoincrement": false
        }
      },
      "indexes": {
        "users_sessions_order_idx": {
          "name": "users_sessions_order_idx",
          "columns": [
            "_order"
          ],
          "isUnique": false
        },
        "users_sessions_parent_id_idx": {
          "name": "users_sessions_parent_id_idx",
          "columns": [
            "_parent_id"
          ],
          "isUnique": false
        }
      },
      "foreignKeys": {
        "users_sessions_parent_id_fk": {
          "name": "users_sessions_parent_id_fk",
          "tableFrom": "users_sessions",
          "tableTo": "users",
          "columnsFrom": [
            "_parent_id"
          ],
          "columnsTo": [
            "id"
          ],
          "onDelete": "cascade",
          "onUpdate": "no action"
        }
      },
      "compositePrimaryKeys": {},
      "uniqueConstraints": {},
      "checkConstraints": {}
    },
    "users": {
      "name": "users",
      "columns": {
        "id": {
          "name": "id",
          "type": "integer",
          "primaryKey": true,
          "notNull": true,
          "autoincrement": false
        },
        "updated_at": {
          "name": "updated_at",
          "type": "text",
          "primaryKey": false,
          "notNull": true,
          "autoincrement": false,
          "default": "(strftime('%Y-%m-%dT%H:%M:%fZ', 'now'))"
        },
        "created_at": {
          "name": "created_at",
          "type": "text",
          "primaryKey": false,
          "notNull": true,
          "autoincrement": false,
          "default": "(strftime('%Y-%m-%dT%H:%M:%fZ', 'now'))"
        },
        "enable_a_p_i_key": {
          "name": "enable_a_p_i_key",
          "type": "integer",
          "primaryKey": false,
          "notNull": false,
          "autoincrement": false
        },
        "api_key": {
          "name": "api_key",
          "type": "text",
          "primaryKey": false,
          "notNull": false,
          "autoincrement": false
        },
        "api_key_index": {
          "name": "api_key_index",
          "type": "text",
          "primaryKey": false,
          "notNull": false,
          "autoincrement": false
        },
        "email": {
          "name": "email",
          "type": "text",
          "primaryKey": false,
          "notNull": true,
          "autoincrement": false
        },
        "reset_password_token": {
          "name": "reset_password_token",
          "type": "text",
          "primaryKey": false,
          "notNull": false,
          "autoincrement": false
        },
        "reset_password_expiration": {
          "name": "reset_password_expiration",
          "type": "text",
          "primaryKey": false,
          "notNull": false,
          "autoincrement": false
        },
        "salt": {
          "name": "salt",
          "type": "text",
          "primaryKey": false,
          "notNull": false,
          "autoincrement": false
        },
        "hash": {
          "name": "hash",
          "type": "text",
          "primaryKey": false,
          "notNull": false,
          "autoincrement": false
        },
        "login_attempts": {
          "name": "login_attempts",
          "type": "numeric",
          "primaryKey": false,
          "notNull": false,
          "autoincrement": false,
          "default": 0
        },
        "lock_until": {
          "name": "lock_until",
          "type": "text",
          "primaryKey": false,
          "notNull": false,
          "autoincrement": false
        }
      },
      "indexes": {
        "users_updated_at_idx": {
          "name": "users_updated_at_idx",
          "columns": [
            "updated_at"
          ],
          "isUnique": false
        },
        "users_created_at_idx": {
          "name": "users_created_at_idx",
          "columns": [
            "created_at"
          ],
          "isUnique": false
        },
        "users_email_idx": {
          "name": "users_email_idx",
          "columns": [
            "email"
          ],
          "isUnique": true
        }
      },
      "foreignKeys": {},
      "compositePrimaryKeys": {},
      "uniqueConstraints": {},
      "checkConstraints": {}
    },
    "service_accounts_roles": {
      "name": "service_accounts_roles",
      "columns": {
        "order": {
          "name": "order",
          "type": "integer",
          "primaryKey": false,
          "notNull": true,
          "autoincrement": false
        },
        "parent_id": {
          "name": "parent_id",
          "type": "integer",
          "primaryKey": false,
          "notNull": true,
          "autoincrement": false
        },
        "value": {
          "name": "value",
          "type": "text",
          "primaryKey": false,
          "notNull": false,
          "autoincrement": false
        },
        "id": {
          "name": "id",
          "type": "integer",
          "primaryKey": true,
          "notNull": true,
          "autoincrement": false
        }
      },
      "indexes": {
        "service_accounts_roles_order_idx": {
          "name": "service_accounts_roles_order_idx",
          "columns": [
            "order"
          ],
          "isUnique": false
        },
        "service_accounts_roles_parent_idx": {
          "name": "service_accounts_roles_parent_idx",
          "columns": [
            "parent_id"
          ],
          "isUnique": false
        }
      },
      "foreignKeys": {
        "service_accounts_roles_parent_fk": {
          "name": "service_accounts_roles_parent_fk",
          "tableFrom": "service_accounts_roles",
          "tableTo": "service_accounts",
          "columnsFrom": [
            "parent_id"
          ],
          "columnsTo": [
            "id"
          ],
          "onDelete": "cascade",
          "onUpdate": "no action"
        }
      },
      "compositePrimaryKeys": {},
      "uniqueConstraints": {},
      "checkConstraints": {}
    },
    "service_accounts": {
      "name": "service_accounts",
      "columns": {
        "id": {
          "name": "id",
          "type": "integer",
          "primaryKey": true,
          "notNull": true,
          "autoincrement": false
        },
        "name": {
          "name": "name",
          "type": "text",
          "primaryKey": false,
          "notNull": true,
          "autoincrement": false
        },
        "revoked": {
          "name": "revoked",
          "type": "integer",
          "primaryKey": false,
          "notNull": true,
          "autoincrement": false,
          "default": false
        },
        "updated_at": {
          "name": "updated_at",
          "type": "text",
          "primaryKey": false,
          "notNull": true,
          "autoincrement": false,
          "default": "(strftime('%Y-%m-%dT%H:%M:%fZ', 'now'))"
        },
        "created_at": {
          "name": "created_at",
          "type": "text",
          "primaryKey": false,
          "notNull": true,
          "autoincrement": false,
          "default": "(strftime('%Y-%m-%dT%H:%M:%fZ', 'now'))"
        },
        "enable_a_p_i_key": {
          "name": "enable_a_p_i_key",
          "type": "integer",
          "primaryKey": false,
          "notNull": false,
          "autoincrement": false
        },
        "api_key": {
          "name": "api_key",
          "type": "text",
          "primaryKey": false,
          "notNull": false,
          "autoincrement": false
        },
        "api_key_index": {
          "name": "api_key_index",
          "type": "text",
          "primaryKey": false,
          "notNull": false,
          "autoincrement": false
        }
      },
      "indexes": {
        "service_accounts_updated_at_idx": {
          "name": "service_accounts_updated_at_idx",
          "columns": [
            "updated_at"
          ],
          "isUnique": false
        },
        "service_accounts_created_at_idx": {
          "name": "service_accounts_created_at_idx",
          "columns": [
            "created_at"
          ],
          "isUnique": false
        }
      },
      "foreignKeys": {},
      "compositePrimaryKeys": {},
      "uniqueConstraints": {},
      "checkConstraints": {}
    },
    "media": {
      "name": "media",
      "columns": {
        "id": {
          "name": "id",
          "type": "integer",
          "primaryKey": true,
          "notNull": true,
          "autoincrement": false
        },
        "alt": {
          "name": "alt",
          "type": "text",
          "primaryKey": false,
          "notNull": true,
          "autoincrement": false
        },
        "batch_id": {
          "name": "batch_id",
          "type": "text",
          "primaryKey": false,
          "notNull": false,
          "autoincrement": false
        },
        "discord_message_id": {
          "name": "discord_message_id",
          "type": "text",
          "primaryKey": false,
          "notNull": false,
          "autoincrement": false
        },
        "discord_user_id": {
          "name": "discord_user_id",
          "type": "text",
          "primaryKey": false,
          "notNull": false,
          "autoincrement": false
        },
        "source": {
          "name": "source",
          "type": "text",
          "primaryKey": false,
          "notNull": false,
          "autoincrement": false,
          "default": "'manual'"
        },
        "updated_at": {
          "name": "updated_at",
          "type": "text",
          "primaryKey": false,
          "notNull": true,
          "autoincrement": false,
          "default": "(strftime('%Y-%m-%dT%H:%M:%fZ', 'now'))"
        },
        "created_at": {
          "name": "created_at",
          "type": "text",
          "primaryKey": false,
          "notNull": true,
          "autoincrement": false,
          "default": "(strftime('%Y-%m-%dT%H:%M:%fZ', 'now'))"
        },
        "url": {
          "name": "url",
          "type": "text",
          "primaryKey": false,
          "notNull": false,
          "autoincrement": false
        },
        "thumbnail_u_r_l": {
          "name": "thumbnail_u_r_l",
          "type": "text",
          "primaryKey": false,
          "notNull": false,
          "autoincrement": false
        },
        "filename": {
          "name": "filename",
          "type": "text",
          "primaryKey": false,
          "notNull": false,
          "autoincrement": false
        },
        "mime_type": {
          "name": "mime_type",
          "type": "text",
          "primaryKey": false,
          "notNull": false,
          "autoincrement": false
        },
        "filesize": {
          "name": "filesize",
          "type": "numeric",
          "primaryKey": false,
          "notNull": false,
          "autoincrement": false
        },
        "width": {
          "name": "width",
          "type": "numeric",
          "primaryKey": false,
          "notNull": false,
          "autoincrement": false
        },
        "height": {
          "name": "height",
          "type": "numeric",
          "primaryKey": false,
          "notNull": false,
          "autoincrement": false
        },
        "focal_x": {
          "name": "focal_x",
          "type": "numeric",
          "primaryKey": false,
          "notNull": false,
          "autoincrement": false
        },
        "focal_y": {
          "name": "focal_y",
          "type": "numeric",
          "primaryKey": false,
          "notNull": false,
          "autoincrement": false
        }
      },
      "indexes": {
        "media_batch_id_idx": {
          "name": "media_batch_id_idx",
          "columns": [
            "batch_id"
          ],
          "isUnique": false
        },
        "media_discord_message_id_idx": {
          "name": "media_discord_message_id_idx",
          "columns": [
            "discord_message_id"
          ],
          "isUnique": false
        },
        "media_discord_user_id_idx": {
          "name": "media_discord_user_id_idx",
          "columns": [
            "discord_user_id"
          ],
          "isUnique": false
        },
        "media_source_idx": {
          "name": "media_source_idx",
          "columns": [
            "source"
          ],
          "isUnique": false
        },
        "media_updated_at_idx": {
          "name": "media_updated_at_idx",
          "columns": [
            "updated_at"
          ],
          "isUnique": false
        },
        "media_created_at_idx": {
          "name": "media_created_at_idx",
          "columns": [
            "created_at"
          ],
          "isUnique": false
        },
        "media_filename_idx": {
          "name": "media_filename_idx",
          "columns": [
            "filename"
          ],
          "isUnique": true
        }
      },
      "foreignKeys": {},
      "compositePrimaryKeys": {},
      "uniqueConstraints": {},
      "checkConstraints": {}
    },
    "events_stats": {
      "name": "events_stats",
      "columns": {
        "_order": {
          "name": "_order",
          "type": "integer",
          "primaryKey": false,
          "notNull": true,
          "autoincrement": false
        },
        "_parent_id": {
          "name": "_parent_id",
          "type": "integer",
          "primaryKey": false,
          "notNull": true,
          "autoincrement": false
        },
        "id": {
          "name": "id",
          "type": "text",
          "primaryKey": true,
          "notNull": true,
          "autoincrement": false
        },
        "data": {
          "name": "data",
          "type": "text",
          "primaryKey": false,
          "notNull": true,
          "autoincrement": false
        },
        "label": {
          "name": "label",
          "type": "text",
          "primaryKey": false,
          "notNull": true,
          "autoincrement": false
        }
      },
      "indexes": {
        "events_stats_order_idx": {
          "name": "events_stats_order_idx",
          "columns": [
            "_order"
          ],
          "isUnique": false
        },
        "events_stats_parent_id_idx": {
          "name": "events_stats_parent_id_idx",
          "columns": [
            "_parent_id"
          ],
          "isUnique": false
        }
      },
      "foreignKeys": {
        "events_stats_parent_id_fk": {
          "name": "events_stats_parent_id_fk",
          "tableFrom": "events_stats",
          "tableTo": "events",
          "columnsFrom": [
            "_parent_id"
          ],
          "columnsTo": [
            "id"
          ],
          "onDelete": "cascade",
          "onUpdate": "no action"
        }
      },
      "compositePrimaryKeys": {},
      "uniqueConstraints": {},
      "checkConstraints": {}
    },
    "events_images": {
      "name": "events_images",
      "columns": {
        "_order": {
          "name": "_order",
          "type": "integer",
          "primaryKey": false,
          "notNull": true,
          "autoincrement": false
        },
        "_parent_id": {
          "name": "_parent_id",
          "type": "integer",
          "primaryKey": false,
          "notNull": true,
          "autoincrement": false
        },
        "id": {
          "name": "id",
          "type": "text",
          "primaryKey": true,
          "notNull": true,
          "autoincrement": false
        },
        "image_id": {
          "name": "image_id",
          "type": "integer",
          "primaryKey": false,
          "notNull": true,
          "autoincrement": false
        }
      },
      "indexes": {
        "events_images_order_idx": {
          "name": "events_images_order_idx",
          "columns": [
            "_order"
          ],
          "isUnique": false
        },
        "events_images_parent_id_idx": {
          "name": "events_images_parent_id_idx",
          "columns": [
            "_parent_id"
          ],
          "isUnique": false
        },
        "events_images_image_idx": {
          "name": "events_images_image_idx",
          "columns": [
            "image_id"
          ],
          "isUnique": false
        }
      },
      "foreignKeys": {
        "events_images_image_id_media_id_fk": {
          "name": "events_images_image_id_media_id_fk",
          "tableFrom": "events_images",
          "tableTo": "media",
          "columnsFrom": [
            "image_id"
          ],
          "columnsTo": [
            "id"
          ],
          "onDelete": "set null",
          "onUpdate": "no action"
        },
        "events_images_parent_id_fk": {
          "name": "events_images_parent_id_fk",
          "tableFrom": "events_images",
          "tableTo": "events",
          "columnsFrom": [
            "_parent_id"
          ],
          "columnsTo": [
            "id"
          ],
          "onDelete": "cascade",
          "onUpdate": "no action"
        }
      },
      "compositePrimaryKeys": {},
      "uniqueConstraints": {},
      "checkConstraints": {}
    },
    "events": {
      "name": "events",
      "columns": {
        "id": {
          "name": "id",
          "type": "integer",
          "primaryKey": true,
          "notNull": true,
          "autoincrement": false
        },
        "name": {
          "name": "name",
          "type": "text",
          "primaryKey": false,
          "notNull": true,
          "autoincrement": false
        },
        "published": {
          "name": "published",
          "type": "integer",
          "primaryKey": false,
          "notNull": true,
          "autoincrement": false,
          "default": false
        },
        "event_type": {
          "name": "event_type",
          "type": "text",
          "primaryKey": false,
          "notNull": true,
          "autoincrement": false,
          "default": "'hack-night'"
        },
        "start": {
          "name": "start",
          "type": "text",
          "primaryKey": false,
          "notNull": true,
          "autoincrement": false
        },
        "end": {
          "name": "end",
          "type": "text",
          "primaryKey": false,
          "notNull": false,
          "autoincrement": false
        },
        "location_name": {
          "name": "location_name",
          "type": "text",
          "primaryKey": false,
          "notNull": false,
          "autoincrement": false
        },
        "location_url": {
          "name": "location_url",
          "type": "text",
          "primaryKey": false,
          "notNull": false,
          "autoincrement": false
        },
        "description": {
          "name": "description",
          "type": "text",
          "primaryKey": false,
          "notNull": true,
          "autoincrement": false
        },
        "send": {
          "name": "send",
          "type": "integer",
          "primaryKey": false,
          "notNull": false,
          "autoincrement": false,
          "default": false
        },
        "sent_at": {
          "name": "sent_at",
          "type": "text",
          "primaryKey": false,
          "notNull": false,
          "autoincrement": false
        },
        "updated_at": {
          "name": "updated_at",
          "type": "text",
          "primaryKey": false,
          "notNull": true,
          "autoincrement": false,
          "default": "(strftime('%Y-%m-%dT%H:%M:%fZ', 'now'))"
        },
        "created_at": {
          "name": "created_at",
          "type": "text",
          "primaryKey": false,
          "notNull": true,
          "autoincrement": false,
          "default": "(strftime('%Y-%m-%dT%H:%M:%fZ', 'now'))"
        }
      },
      "indexes": {
        "events_updated_at_idx": {
          "name": "events_updated_at_idx",
          "columns": [
            "updated_at"
          ],
          "isUnique": false
        },
        "events_created_at_idx": {
          "name": "events_created_at_idx",
          "columns": [
            "created_at"
          ],
          "isUnique": false
        }
      },
      "foreignKeys": {},
      "compositePrimaryKeys": {},
      "uniqueConstraints": {},
      "checkConstraints": {}
    },
    "emails": {
      "name": "emails",
      "columns": {
        "id": {
          "name": "id",
          "type": "integer",
          "primaryKey": true,
          "notNull": true,
          "autoincrement": false
        },
        "event_id": {
          "name": "event_id",
          "type": "integer",
          "primaryKey": false,
          "notNull": true,
          "autoincrement": false
        },
        "subject": {
          "name": "subject",
          "type": "text",
          "primaryKey": false,
          "notNull": true,
          "autoincrement": false,
          "default": "'Reminder: Purdue Hackers event starting soon!!!'"
        },
        "body": {
          "name": "body",
          "type": "text",
          "primaryKey": false,
          "notNull": true,
          "autoincrement": false,
          "default": "'Hi there!\n\nThis is a friendly reminder that the event is coming up soon. We look forward to seeing you there!'"
        },
        "send": {
          "name": "send",
          "type": "integer",
          "primaryKey": false,
          "notNull": false,
          "autoincrement": false,
          "default": false
        },
        "sent_at": {
          "name": "sent_at",
          "type": "text",
          "primaryKey": false,
          "notNull": false,
          "autoincrement": false
        },
        "updated_at": {
          "name": "updated_at",
          "type": "text",
          "primaryKey": false,
          "notNull": true,
          "autoincrement": false,
          "default": "(strftime('%Y-%m-%dT%H:%M:%fZ', 'now'))"
        },
        "created_at": {
          "name": "created_at",
          "type": "text",
          "primaryKey": false,
          "notNull": true,
          "autoincrement": false,
          "default": "(strftime('%Y-%m-%dT%H:%M:%fZ', 'now'))"
        }
      },
      "indexes": {
        "emails_event_idx": {
          "name": "emails_event_idx",
          "columns": [
            "event_id"
          ],
          "isUnique": false
        },
        "emails_updated_at_idx": {
          "name": "emails_updated_at_idx",
          "columns": [
            "updated_at"
          ],
          "isUnique": false
        },
        "emails_created_at_idx": {
          "name": "emails_created_at_idx",
          "columns": [
            "created_at"
          ],
          "isUnique": false
        }
      },
      "foreignKeys": {
        "emails_event_id_events_id_fk": {
          "name": "emails_event_id_events_id_fk",
          "tableFrom": "emails",
          "tableTo": "events",
          "columnsFrom": [
            "event_id"
          ],
          "columnsTo": [
            "id"
          ],
          "onDelete": "set null",
          "onUpdate": "no action"
        }
      },
      "compositePrimaryKeys": {},
      "uniqueConstraints": {},
      "checkConstraints": {}
    },
    "rsvps": {
      "name": "rsvps",
      "columns": {
        "id": {
          "name": "id",
          "type": "integer",
          "primaryKey": true,
          "notNull": true,
          "autoincrement": false
        },
        "email": {
          "name": "email",
          "type": "text",
          "primaryKey": false,
          "notNull": true,
          "autoincrement": false
        },
        "name": {
          "name": "name",
          "type": "text",
          "primaryKey": false,
          "notNull": false,
          "autoincrement": false
        },
        "event_id": {
          "name": "event_id",
          "type": "integer",
          "primaryKey": false,
          "notNull": true,
          "autoincrement": false
        },
        "unsubscribed": {
          "name": "unsubscribed",
          "type": "integer",
          "primaryKey": false,
          "notNull": false,
          "autoincrement": false,
          "default": false
        },
        "updated_at": {
          "name": "updated_at",
          "type": "text",
          "primaryKey": false,
          "notNull": true,
          "autoincrement": false,
          "default": "(strftime('%Y-%m-%dT%H:%M:%fZ', 'now'))"
        },
        "created_at": {
          "name": "created_at",
          "type": "text",
          "primaryKey": false,
          "notNull": true,
          "autoincrement": false,
          "default": "(strftime('%Y-%m-%dT%H:%M:%fZ', 'now'))"
        }
      },
      "indexes": {
        "rsvps_event_idx": {
          "name": "rsvps_event_idx",
          "columns": [
            "event_id"
          ],
          "isUnique": false
        },
        "rsvps_updated_at_idx": {
          "name": "rsvps_updated_at_idx",
          "columns": [
            "updated_at"
          ],
          "isUnique": false
        },
        "rsvps_created_at_idx": {
          "name": "rsvps_created_at_idx",
          "columns": [
            "created_at"
          ],
          "isUnique": false
        }
      },
      "foreignKeys": {
        "rsvps_event_id_events_id_fk": {
          "name": "rsvps_event_id_events_id_fk",
          "tableFrom": "rsvps",
          "tableTo": "events",
          "columnsFrom": [
            "event_id"
          ],
          "columnsTo": [
            "id"
          ],
          "onDelete": "set null",
          "onUpdate": "no action"
        }
      },
      "compositePrimaryKeys": {},
      "uniqueConstraints": {},
      "checkConstraints": {}
    },
    "hack_night_sessions_images": {
      "name": "hack_night_sessions_images",
      "columns": {
        "_order": {
          "name": "_order",
          "type": "integer",
          "primaryKey": false,
          "notNull": true,
          "autoincrement": false
        },
        "_parent_id": {
          "name": "_parent_id",
          "type": "integer",
          "primaryKey": false,
          "notNull": true,
          "autoincrement": false
        },
        "id": {
          "name": "id",
          "type": "text",
          "primaryKey": true,
          "notNull": true,
          "autoincrement": false
        },
        "image_id": {
          "name": "image_id",
          "type": "integer",
          "primaryKey": false,
          "notNull": true,
          "autoincrement": false
        }
      },
      "indexes": {
        "hack_night_sessions_images_order_idx": {
          "name": "hack_night_sessions_images_order_idx",
          "columns": [
            "_order"
          ],
          "isUnique": false
        },
        "hack_night_sessions_images_parent_id_idx": {
          "name": "hack_night_sessions_images_parent_id_idx",
          "columns": [
            "_parent_id"
          ],
          "isUnique": false
        },
        "hack_night_sessions_images_image_idx": {
          "name": "hack_night_sessions_images_image_idx",
          "columns": [
            "image_id"
          ],
          "isUnique": false
        }
      },
      "foreignKeys": {
        "hack_night_sessions_images_image_id_media_id_fk": {
          "name": "hack_night_sessions_images_image_id_media_id_fk",
          "tableFrom": "hack_night_sessions_images",
          "tableTo": "media",
          "columnsFrom": [
            "image_id"
          ],
          "columnsTo": [
            "id"
          ],
          "onDelete": "set null",
          "onUpdate": "no action"
        },
        "hack_night_sessions_images_parent_id_fk": {
          "name": "hack_night_sessions_images_parent_id_fk",
          "tableFrom": "hack_night_sessions_images",
          "tableTo": "hack_night_sessions",
          "columnsFrom": [
            "_parent_id"
          ],
          "columnsTo": [
            "id"
          ],
          "onDelete": "cascade",
          "onUpdate": "no action"
        }
      },
      "compositePrimaryKeys": {},
      "uniqueConstraints": {},
      "checkConstraints": {}
    },
    "hack_night_sessions": {
      "name": "hack_night_sessions",
      "columns": {
        "id": {
          "name": "id",
          "type": "integer",
          "primaryKey": true,
          "notNull": true,
          "autoincrement": false
        },
        "title": {
          "name": "title",
          "type": "text",
          "primaryKey": false,
          "notNull": true,
          "autoincrement": false
        },
        "date": {
          "name": "date",
          "type": "text",
          "primaryKey": false,
          "notNull": true,
          "autoincrement": false
        },
        "published": {
          "name": "published",
          "type": "integer",
          "primaryKey": false,
          "notNull": true,
          "autoincrement": false,
          "default": false
        },
        "host_preferred_name": {
          "name": "host_preferred_name",
          "type": "text",
          "primaryKey": false,
          "notNull": true,
          "autoincrement": false
        },
        "host_discord_id": {
          "name": "host_discord_id",
          "type": "text",
          "primaryKey": false,
          "notNull": false,
          "autoincrement": false
        },
        "description": {
          "name": "description",
          "type": "text",
          "primaryKey": false,
          "notNull": true,
          "autoincrement": false
        },
        "updated_at": {
          "name": "updated_at",
          "type": "text",
          "primaryKey": false,
          "notNull": true,
          "autoincrement": false,
          "default": "(strftime('%Y-%m-%dT%H:%M:%fZ', 'now'))"
        },
        "created_at": {
          "name": "created_at",
          "type": "text",
          "primaryKey": false,
          "notNull": true,
          "autoincrement": false,
          "default": "(strftime('%Y-%m-%dT%H:%M:%fZ', 'now'))"
        }
      },
      "indexes": {
        "hack_night_sessions_date_idx": {
          "name": "hack_night_sessions_date_idx",
          "columns": [
            "date"
          ],
          "isUnique": false
        },
        "hack_night_sessions_updated_at_idx": {
          "name": "hack_night_sessions_updated_at_idx",
          "columns": [
            "updated_at"
          ],
          "isUnique": false
        },
        "hack_night_sessions_created_at_idx": {
          "name": "hack_night_sessions_created_at_idx",
          "columns": [
            "created_at"
          ],
          "isUnique": false
        }
      },
      "foreignKeys": {},
      "compositePrimaryKeys": {},
      "uniqueConstraints": {},
      "checkConstraints": {}
    },
    "shelter": {
      "name": "shelter",
      "columns": {
        "id": {
          "name": "id",
          "type": "integer",
          "primaryKey": true,
          "notNull": true,
          "autoincrement": false
        },
        "visible": {
          "name": "visible",
          "type": "integer",
          "primaryKey": false,
          "notNull": false,
          "autoincrement": false,
          "default": true
        },
        "name": {
          "name": "name",
          "type": "text",
          "primaryKey": false,
          "notNull": true,
          "autoincrement": false
        },
        "last_division": {
          "name": "last_division",
          "type": "text",
          "primaryKey": false,
          "notNull": true,
          "autoincrement": false
        },
        "last_owner": {
          "name": "last_owner",
          "type": "text",
          "primaryKey": false,
          "notNull": true,
          "autoincrement": false
        },
        "description": {
          "name": "description",
          "type": "text",
          "primaryKey": false,
          "notNull": true,
          "autoincrement": false
        },
        "image_id": {
          "name": "image_id",
          "type": "integer",
          "primaryKey": false,
          "notNull": true,
          "autoincrement": false
        },
        "updated_at": {
          "name": "updated_at",
          "type": "text",
          "primaryKey": false,
          "notNull": true,
          "autoincrement": false,
          "default": "(strftime('%Y-%m-%dT%H:%M:%fZ', 'now'))"
        },
        "created_at": {
          "name": "created_at",
          "type": "text",
          "primaryKey": false,
          "notNull": true,
          "autoincrement": false,
          "default": "(strftime('%Y-%m-%dT%H:%M:%fZ', 'now'))"
        }
      },
      "indexes": {
        "shelter_image_idx": {
          "name": "shelter_image_idx",
          "columns": [
            "image_id"
          ],
          "isUnique": false
        },
        "shelter_updated_at_idx": {
          "name": "shelter_updated_at_idx",
          "columns": [
            "updated_at"
          ],
          "isUnique": false
        },
        "shelter_created_at_idx": {
          "name": "shelter_created_at_idx",
          "columns": [
            "created_at"
          ],
          "isUnique": false
        }
      },
      "foreignKeys": {
        "shelter_image_id_media_id_fk": {
          "name": "shelter_image_id_media_id_fk",
          "tableFrom": "shelter",
          "tableTo": "media",
          "columnsFrom": [
            "image_id"
          ],
          "columnsTo": [
            "id"
          ],
          "onDelete": "set null",
          "onUpdate": "no action"
        }
      },
      "compositePrimaryKeys": {},
      "uniqueConstraints": {},
      "checkConstraints": {}
    },
    "microgrants": {
      "name": "microgrants",
      "columns": {
        "id": {
          "name": "id",
          "type": "integer",
          "primaryKey": true,
          "notNull": true,
          "autoincrement": false
        },
        "visible": {
          "name": "visible",
          "type": "integer",
          "primaryKey": false,
          "notNull": false,
          "autoincrement": false,
          "default": true
        },
        "name": {
          "name": "name",
          "type": "text",
          "primaryKey": false,
          "notNull": true,
          "autoincrement": false
        },
        "author": {
          "name": "author",
          "type": "text",
          "primaryKey": false,
          "notNull": true,
          "autoincrement": false
        },
        "description": {
          "name": "description",
          "type": "text",
          "primaryKey": false,
          "notNull": true,
          "autoincrement": false
        },
        "image_id": {
          "name": "image_id",
          "type": "integer",
          "primaryKey": false,
          "notNull": true,
          "autoincrement": false
        },
        "author_url": {
          "name": "author_url",
          "type": "text",
          "primaryKey": false,
          "notNull": false,
          "autoincrement": false
        },
        "project_url": {
          "name": "project_url",
          "type": "text",
          "primaryKey": false,
          "notNull": false,
          "autoincrement": false
        },
        "updated_at": {
          "name": "updated_at",
          "type": "text",
          "primaryKey": false,
          "notNull": true,
          "autoincrement": false,
          "default": "(strftime('%Y-%m-%dT%H:%M:%fZ', 'now'))"
        },
        "created_at": {
          "name": "created_at",
          "type": "text",
          "primaryKey": false,
          "notNull": true,
          "autoincrement": false,
          "default": "(strftime('%Y-%m-%dT%H:%M:%fZ', 'now'))"
        }
      },
      "indexes": {
        "microgrants_image_idx": {
          "name": "microgrants_image_idx",
          "columns": [
            "image_id"
          ],
          "isUnique": false
        },
        "microgrants_updated_at_idx": {
          "name": "microgrants_updated_at_idx",
          "columns": [
            "updated_at"
          ],
          "isUnique": false
        },
        "microgrants_created_at_idx": {
          "name": "microgrants_created_at_idx",
          "columns": [
            "created_at"
          ],
          "isUnique": false
        }
      },
      "foreignKeys": {
        "microgrants_image_id_media_id_fk": {
          "name": "microgrants_image_id_media_id_fk",
          "tableFrom": "microgrants",
          "tableTo": "media",
          "columnsFrom": [
            "image_id"
          ],
          "columnsTo": [
            "id"
          ],
          "onDelete": "set null",
          "onUpdate": "no action"
        }
      },
      "compositePrimaryKeys": {},
      "uniqueConstraints": {},
      "checkConstraints": {}
    },
    "redirects": {
      "name": "redirects",
      "columns": {
        "id": {
          "name": "id",
          "type": "integer",
          "primaryKey": true,
          "notNull": true,
          "autoincrement": false
        },
        "from": {
          "name": "from",
          "type": "text",
          "primaryKey": false,
          "notNull": true,
          "autoincrement": false
        },
        "to_type": {
          "name": "to_type",
          "type": "text",
          "primaryKey": false,
          "notNull": false,
          "autoincrement": false,
          "default": "'reference'"
        },
        "to_url": {
          "name": "to_url",
          "type": "text",
          "primaryKey": false,
          "notNull": false,
          "autoincrement": false
        },
        "updated_at": {
          "name": "updated_at",
          "type": "text",
          "primaryKey": false,
          "notNull": true,
          "autoincrement": false,
          "default": "(strftime('%Y-%m-%dT%H:%M:%fZ', 'now'))"
        },
        "created_at": {
          "name": "created_at",
          "type": "text",
          "primaryKey": false,
          "notNull": true,
          "autoincrement": false,
          "default": "(strftime('%Y-%m-%dT%H:%M:%fZ', 'now'))"
        }
      },
      "indexes": {
        "redirects_from_idx": {
          "name": "redirects_from_idx",
          "columns": [
            "from"
          ],
          "isUnique": true
        },
        "redirects_updated_at_idx": {
          "name": "redirects_updated_at_idx",
          "columns": [
            "updated_at"
          ],
          "isUnique": false
        },
        "redirects_created_at_idx": {
          "name": "redirects_created_at_idx",
          "columns": [
            "created_at"
          ],
          "isUnique": false
        }
      },
      "foreignKeys": {},
      "compositePrimaryKeys": {},
      "uniqueConstraints": {},
      "checkConstraints": {}
    },
    "redirects_rels": {
      "name": "redirects_rels",
      "columns": {
        "id": {
          "name": "id",
          "type": "integer",
          "primaryKey": true,
          "notNull": true,
          "autoincrement": false
        },
        "order": {
          "name": "order",
          "type": "integer",
          "primaryKey": false,
          "notNull": false,
          "autoincrement": false
        },
        "parent_id": {
          "name": "parent_id",
          "type": "integer",
          "primaryKey": false,
          "notNull": true,
          "autoincrement": false
        },
        "path": {
          "name": "path",
          "type": "text",
          "primaryKey": false,
          "notNull": true,
          "autoincrement": false
        },
        "events_id": {
          "name": "events_id",
          "type": "integer",
          "primaryKey": false,
          "notNull": false,
          "autoincrement": false
        },
        "shelter_id": {
          "name": "shelter_id",
          "type": "integer",
          "primaryKey": false,
          "notNull": false,
          "autoincrement": false
        },
        "microgrants_id": {
          "name": "microgrants_id",
          "type": "integer",
          "primaryKey": false,
          "notNull": false,
          "autoincrement": false
        },
        "hack_night_sessions_id": {
          "name": "hack_night_sessions_id",
          "type": "integer",
          "primaryKey": false,
          "notNull": false,
          "autoincrement": false
        }
      },
      "indexes": {
        "redirects_rels_order_idx": {
          "name": "redirects_rels_order_idx",
          "columns": [
            "order"
          ],
          "isUnique": false
        },
        "redirects_rels_parent_idx": {
          "name": "redirects_rels_parent_idx",
          "columns": [
            "parent_id"
          ],
          "isUnique": false
        },
        "redirects_rels_path_idx": {
          "name": "redirects_rels_path_idx",
          "columns": [
            "path"
          ],
          "isUnique": false
        },
        "redirects_rels_events_id_idx": {
          "name": "redirects_rels_events_id_idx",
          "columns": [
            "events_id"
          ],
          "isUnique": false
        },
        "redirects_rels_shelter_id_idx": {
          "name": "redirects_rels_shelter_id_idx",
          "columns": [
            "shelter_id"
          ],
          "isUnique": false
        },
        "redirects_rels_microgrants_id_idx": {
          "name": "redirects_rels_microgrants_id_idx",
          "columns": [
            "microgrants_id"
          ],
          "isUnique": false
        },
        "redirects_rels_hack_night_sessions_id_idx": {
          "name": "redirects_rels_hack_night_sessions_id_idx",
          "columns": [
            "hack_night_sessions_id"
          ],
          "isUnique": false
        }
      },
      "foreignKeys": {
        "redirects_rels_parent_fk": {
          "name": "redirects_rels_parent_fk",
          "tableFrom": "redirects_rels",
          "tableTo": "redirects",
          "columnsFrom": [
            "parent_id"
          ],
          "columnsTo": [
            "id"
          ],
          "onDelete": "cascade",
          "onUpdate": "no action"
        },
        "redirects_rels_events_fk": {
          "name": "redirects_rels_events_fk",
          "tableFrom": "redirects_rels",
          "tableTo": "events",
          "columnsFrom": [
            "events_id"
          ],
          "columnsTo": [
            "id"
          ],
          "onDelete": "cascade",
          "onUpdate": "no action"
        },
        "redirects_rels_shelter_fk": {
          "name": "redirects_rels_shelter_fk",
          "tableFrom": "redirects_rels",
          "tableTo": "shelter",
          "columnsFrom": [
            "shelter_id"
          ],
          "columnsTo": [
            "id"
          ],
          "onDelete": "cascade",
          "onUpdate": "no action"
        },
        "redirects_rels_microgrants_fk": {
          "name": "redirects_rels_microgrants_fk",
          "tableFrom": "redirects_rels",
          "tableTo": "microgrants",
          "columnsFrom": [
            "microgrants_id"
          ],
          "columnsTo": [
            "id"
          ],
          "onDelete": "cascade",
          "onUpdate": "no action"
        },
        "redirects_rels_hack_night_sessions_fk": {
          "name": "redirects_rels_hack_night_sessions_fk",
          "tableFrom": "redirects_rels",
          "tableTo": "hack_night_sessions",
          "columnsFrom": [
            "hack_night_sessions_id"
          ],
          "columnsTo": [
            "id"
          ],
          "onDelete": "cascade",
          "onUpdate": "no action"
        }
      },
      "compositePrimaryKeys": {},
      "uniqueConstraints": {},
      "checkConstraints": {}
    },
    "search": {
      "name": "search",
      "columns": {
        "id": {
          "name": "id",
          "type": "integer",
          "primaryKey": true,
          "notNull": true,
          "autoincrement": false
        },
        "title": {
          "name": "title",
          "type": "text",
          "primaryKey": false,
          "notNull": false,
          "autoincrement": false
        },
        "priority": {
          "name": "priority",
          "type": "numeric",
          "primaryKey": false,
          "notNull": false,
          "autoincrement": false
        },
        "updated_at": {
          "name": "updated_at",
          "type": "text",
          "primaryKey": false,
          "notNull": true,
          "autoincrement": false,
          "default": "(strftime('%Y-%m-%dT%H:%M:%fZ', 'now'))"
        },
        "created_at": {
          "name": "created_at",
          "type": "text",
          "primaryKey": false,
          "notNull": true,
          "autoincrement": false,
          "default": "(strftime('%Y-%m-%dT%H:%M:%fZ', 'now'))"
        }
      },
      "indexes": {
        "search_updated_at_idx": {
          "name": "search_updated_at_idx",
          "columns": [
            "updated_at"
          ],
          "isUnique": false
        },
        "search_created_at_idx": {
          "name": "search_created_at_idx",
          "columns": [
            "created_at"
          ],
          "isUnique": false
        }
      },
      "foreignKeys": {},
      "compositePrimaryKeys": {},
      "uniqueConstraints": {},
      "checkConstraints": {}
    },
    "search_rels": {
      "name": "search_rels",
      "columns": {
        "id": {
          "name": "id",
          "type": "integer",
          "primaryKey": true,
          "notNull": true,
          "autoincrement": false
        },
        "order": {
          "name": "order",
          "type": "integer",
          "primaryKey": false,
          "notNull": false,
          "autoincrement": false
        },
        "parent_id": {
          "name": "parent_id",
          "type": "integer",
          "primaryKey": false,
          "notNull": true,
          "autoincrement": false
        },
        "path": {
          "name": "path",
          "type": "text",
          "primaryKey": false,
          "notNull": true,
          "autoincrement": false
        },
        "events_id": {
          "name": "events_id",
          "type": "integer",
          "primaryKey": false,
          "notNull": false,
          "autoincrement": false
        },
        "shelter_id": {
          "name": "shelter_id",
          "type": "integer",
          "primaryKey": false,
          "notNull": false,
          "autoincrement": false
        },
        "microgrants_id": {
          "name": "microgrants_id",
          "type": "integer",
          "primaryKey": false,
          "notNull": false,
          "autoincrement": false
        },
        "hack_night_sessions_id": {
          "name": "hack_night_sessions_id",
          "type": "integer",
          "primaryKey": false,
          "notNull": false,
          "autoincrement": false
        }
      },
      "indexes": {
        "search_rels_order_idx": {
          "name": "search_rels_order_idx",
          "columns": [
            "order"
          ],
          "isUnique": false
        },
        "search_rels_parent_idx": {
          "name": "search_rels_parent_idx",
          "columns": [
            "parent_id"
          ],
          "isUnique": false
        },
        "search_rels_path_idx": {
          "name": "search_rels_path_idx",
          "columns": [
            "path"
          ],
          "isUnique": false
        },
        "search_rels_events_id_idx": {
          "name": "search_rels_events_id_idx",
          "columns": [
            "events_id"
          ],
          "isUnique": false
        },
        "search_rels_shelter_id_idx": {
          "name": "search_rels_shelter_id_idx",
          "columns": [
            "shelter_id"
          ],
          "isUnique": false
        },
        "search_rels_microgrants_id_idx": {
          "name": "search_rels_microgrants_id_idx",
          "columns": [
            "microgrants_id"
          ],
          "isUnique": false
        },
        "search_rels_hack_night_sessions_id_idx": {
          "name": "search_rels_hack_night_sessions_id_idx",
          "columns": [
            "hack_night_sessions_id"
          ],
          "isUnique": false
        }
      },
      "foreignKeys": {
        "search_rels_parent_fk": {
          "name": "search_rels_parent_fk",
          "tableFrom": "search_rels",
          "tableTo": "search",
          "columnsFrom": [
            "parent_id"
          ],
          "columnsTo": [
            "id"
          ],
          "onDelete": "cascade",
          "onUpdate": "no action"
        },
        "search_rels_events_fk": {
          "name": "search_rels_events_fk",
          "tableFrom": "search_rels",
          "tableTo": "events",
          "columnsFrom": [
            "events_id"
          ],
          "columnsTo": [
            "id"
          ],
          "onDelete": "cascade",
          "onUpdate": "no action"
        },
        "search_rels_shelter_fk": {
          "name": "search_rels_shelter_fk",
          "tableFrom": "search_rels",
          "tableTo": "shelter",
          "columnsFrom": [
            "shelter_id"
          ],
          "columnsTo": [
            "id"
          ],
          "onDelete": "cascade",
          "onUpdate": "no action"
        },
        "search_rels_microgrants_fk": {
          "name": "search_rels_microgrants_fk",
          "tableFrom": "search_rels",
          "tableTo": "microgrants",
          "columnsFrom": [
            "microgrants_id"
          ],
          "columnsTo": [
            "id"
          ],
          "onDelete": "cascade",
          "onUpdate": "no action"
        },
        "search_rels_hack_night_sessions_fk": {
          "name": "search_rels_hack_night_sessions_fk",
          "tableFrom": "search_rels",
          "tableTo": "hack_night_sessions",
          "columnsFrom": [
            "hack_night_sessions_id"
          ],
          "columnsTo": [
            "id"
          ],
          "onDelete": "cascade",
          "onUpdate": "no action"
        }
      },
      "compositePrimaryKeys": {},
      "uniqueConstraints": {},
      "checkConstraints": {}
    },
    "payload_mcp_api_keys": {
      "name": "payload_mcp_api_keys",
      "columns": {
        "id": {
          "name": "id",
          "type": "integer",
          "primaryKey": true,
          "notNull": true,
          "autoincrement": false
        },
        "user_id": {
          "name": "user_id",
          "type": "integer",
          "primaryKey": false,
          "notNull": true,
          "autoincrement": false
        },
        "label": {
          "name": "label",
          "type": "text",
          "primaryKey": false,
          "notNull": false,
          "autoincrement": false
        },
        "description": {
          "name": "description",
          "type": "text",
          "primaryKey": false,
          "notNull": false,
          "autoincrement": false
        },
        "events_find": {
          "name": "events_find",
          "type": "integer",
          "primaryKey": false,
          "notNull": false,
          "autoincrement": false,
          "default": false
        },
        "rsvps_find": {
          "name": "rsvps_find",
          "type": "integer",
          "primaryKey": false,
          "notNull": false,
          "autoincrement": false,
          "default": false
        },
        "hack_night_sessions_find": {
          "name": "hack_night_sessions_find",
          "type": "integer",
          "primaryKey": false,
          "notNull": false,
          "autoincrement": false,
          "default": false
        },
        "shelter_find": {
          "name": "shelter_find",
          "type": "integer",
          "primaryKey": false,
          "notNull": false,
          "autoincrement": false,
          "default": false
        },
        "microgrants_find": {
          "name": "microgrants_find",
          "type": "integer",
          "primaryKey": false,
          "notNull": false,
          "autoincrement": false,
          "default": false
        },
        "updated_at": {
          "name": "updated_at",
          "type": "text",
          "primaryKey": false,
          "notNull": true,
          "autoincrement": false,
          "default": "(strftime('%Y-%m-%dT%H:%M:%fZ', 'now'))"
        },
        "created_at": {
          "name": "created_at",
          "type": "text",
          "primaryKey": false,
          "notNull": true,
          "autoincrement": false,
          "default": "(strftime('%Y-%m-%dT%H:%M:%fZ', 'now'))"
        },
        "enable_a_p_i_key": {
          "name": "enable_a_p_i_key",
          "type": "integer",
          "primaryKey": false,
          "notNull": false,
          "autoincrement": false
        },
        "api_key": {
          "name": "api_key",
          "type": "text",
          "primaryKey": false,
          "notNull": false,
          "autoincrement": false
        },
        "api_key_index": {
          "name": "api_key_index",
          "type": "text",
          "primaryKey": false,
          "notNull": false,
          "autoincrement": false
        }
      },
      "indexes": {
        "payload_mcp_api_keys_user_idx": {
          "name": "payload_mcp_api_keys_user_idx",
          "columns": [
            "user_id"
          ],
          "isUnique": false
        },
        "payload_mcp_api_keys_updated_at_idx": {
          "name": "payload_mcp_api_keys_updated_at_idx",
          "columns": [
            "updated_at"
          ],
          "isUnique": false
        },
        "payload_mcp_api_keys_created_at_idx": {
          "name": "payload_mcp_api_keys_created_at_idx",
          "columns": [
            "created_at"
          ],
          "isUnique": false
        }
      },
      "foreignKeys": {
        "payload_mcp_api_keys_user_id_users_id_fk": {
          "name": "payload_mcp_api_keys_user_id_users_id_fk",
          "tableFrom": "payload_mcp_api_keys",
          "tableTo": "users",
          "columnsFrom": [
            "user_id"
          ],
          "columnsTo": [
            "id"
          ],
          "onDelete": "set null",
          "onUpdate": "no action"
        }
      },
      "compositePrimaryKeys": {},
      "uniqueConstraints": {},
      "checkConstraints": {}
    },
    "payload_kv": {
      "name": "payload_kv",
      "columns": {
        "id": {
          "name": "id",
          "type": "integer",
          "primaryKey": true,
          "notNull": true,
          "autoincrement": false
        },
        "key": {
          "name": "key",
          "type": "text",
          "primaryKey": false,
          "notNull": true,
          "autoincrement": false
        },
        "data": {
          "name": "data",
          "type": "text",
          "primaryKey": false,
          "notNull": true,
          "autoincrement": false
        }
      },
      "indexes": {
        "payload_kv_key_idx": {
          "name": "payload_kv_key_idx",
          "columns": [
            "key"
          ],
          "isUnique": true
        }
      },
      "foreignKeys": {},
      "compositePrimaryKeys": {},
      "uniqueConstraints": {},
      "checkConstraints": {}
    },
    "payload_locked_documents": {
      "name": "payload_locked_documents",
      "columns": {
        "id": {
          "name": "id",
          "type": "integer",
          "primaryKey": true,
          "notNull": true,
          "autoincrement": false
        },
        "global_slug": {
          "name": "global_slug",
          "type": "text",
          "primaryKey": false,
          "notNull": false,
          "autoincrement": false
        },
        "updated_at": {
          "name": "updated_at",
          "type": "text",
          "primaryKey": false,
          "notNull": true,
          "autoincrement": false,
          "default": "(strftime('%Y-%m-%dT%H:%M:%fZ', 'now'))"
        },
        "created_at": {
          "name": "created_at",
          "type": "text",
          "primaryKey": false,
          "notNull": true,
          "autoincrement": false,
          "default": "(strftime('%Y-%m-%dT%H:%M:%fZ', 'now'))"
        }
      },
      "indexes": {
        "payload_locked_documents_global_slug_idx": {
          "name": "payload_locked_documents_global_slug_idx",
          "columns": [
            "global_slug"
          ],
          "isUnique": false
        },
        "payload_locked_documents_updated_at_idx": {
          "name": "payload_locked_documents_updated_at_idx",
          "columns": [
            "updated_at"
          ],
          "isUnique": false
        },
        "payload_locked_documents_created_at_idx": {
          "name": "payload_locked_documents_created_at_idx",
          "columns": [
            "created_at"
          ],
          "isUnique": false
        }
      },
      "foreignKeys": {},
      "compositePrimaryKeys": {},
      "uniqueConstraints": {},
      "checkConstraints": {}
    },
    "payload_locked_documents_rels": {
      "name": "payload_locked_documents_rels",
      "columns": {
        "id": {
          "name": "id",
          "type": "integer",
          "primaryKey": true,
          "notNull": true,
          "autoincrement": false
        },
        "order": {
          "name": "order",
          "type": "integer",
          "primaryKey": false,
          "notNull": false,
          "autoincrement": false
        },
        "parent_id": {
          "name": "parent_id",
          "type": "integer",
          "primaryKey": false,
          "notNull": true,
          "autoincrement": false
        },
        "path": {
          "name": "path",
          "type": "text",
          "primaryKey": false,
          "notNull": true,
          "autoincrement": false
        },
        "users_id": {
          "name": "users_id",
          "type": "integer",
          "primaryKey": false,
          "notNull": false,
          "autoincrement": false
        },
        "service_accounts_id": {
          "name": "service_accounts_id",
          "type": "integer",
          "primaryKey": false,
          "notNull": false,
          "autoincrement": false
        },
        "media_id": {
          "name": "media_id",
          "type": "integer",
          "primaryKey": false,
          "notNull": false,
          "autoincrement": false
        },
        "events_id": {
          "name": "events_id",
          "type": "integer",
          "primaryKey": false,
          "notNull": false,
          "autoincrement": false
        },
        "emails_id": {
          "name": "emails_id",
          "type": "integer",
          "primaryKey": false,
          "notNull": false,
          "autoincrement": false
        },
        "rsvps_id": {
          "name": "rsvps_id",
          "type": "integer",
          "primaryKey": false,
          "notNull": false,
          "autoincrement": false
        },
        "hack_night_sessions_id": {
          "name": "hack_night_sessions_id",
          "type": "integer",
          "primaryKey": false,
          "notNull": false,
          "autoincrement": false
        },
        "shelter_id": {
          "name": "shelter_id",
          "type": "integer",
          "primaryKey": false,
          "notNull": false,
          "autoincrement": false
        },
        "microgrants_id": {
          "name": "microgrants_id",
          "type": "integer",
          "primaryKey": false,
          "notNull": false,
          "autoincrement": false
        },
        "redirects_id": {
          "name": "redirects_id",
          "type": "integer",
          "primaryKey": false,
          "notNull": false,
          "autoincrement": false
        },
        "search_id": {
          "name": "search_id",
          "type": "integer",
          "primaryKey": false,
          "notNull": false,
          "autoincrement": false
        },
        "payload_mcp_api_keys_id": {
          "name": "payload_mcp_api_keys_id",
          "type": "integer",
          "primaryKey": false,
          "notNull": false,
          "autoincrement": false
        }
      },
      "indexes": {
        "payload_locked_documents_rels_order_idx": {
          "name": "payload_locked_documents_rels_order_idx",
          "columns": [
            "order"
          ],
          "isUnique": false
        },
        "payload_locked_documents_rels_parent_idx": {
          "name": "payload_locked_documents_rels_parent_idx",
          "columns": [
            "parent_id"
          ],
          "isUnique": false
        },
        "payload_locked_documents_rels_path_idx": {
          "name": "payload_locked_documents_rels_path_idx",
          "columns": [
            "path"
          ],
          "isUnique": false
        },
        "payload_locked_documents_rels_users_id_idx": {
          "name": "payload_locked_documents_rels_users_id_idx",
          "columns": [
            "users_id"
          ],
          "isUnique": false
        },
        "payload_locked_documents_rels_service_accounts_id_idx": {
          "name": "payload_locked_documents_rels_service_accounts_id_idx",
          "columns": [
            "service_accounts_id"
          ],
          "isUnique": false
        },
        "payload_locked_documents_rels_media_id_idx": {
          "name": "payload_locked_documents_rels_media_id_idx",
          "columns": [
            "media_id"
          ],
          "isUnique": false
        },
        "payload_locked_documents_rels_events_id_idx": {
          "name": "payload_locked_documents_rels_events_id_idx",
          "columns": [
            "events_id"
          ],
          "isUnique": false
        },
        "payload_locked_documents_rels_emails_id_idx": {
          "name": "payload_locked_documents_rels_emails_id_idx",
          "columns": [
            "emails_id"
          ],
          "isUnique": false
        },
        "payload_locked_documents_rels_rsvps_id_idx": {
          "name": "payload_locked_documents_rels_rsvps_id_idx",
          "columns": [
            "rsvps_id"
          ],
          "isUnique": false
        },
        "payload_locked_documents_rels_hack_night_sessions_id_idx": {
          "name": "payload_locked_documents_rels_hack_night_sessions_id_idx",
          "columns": [
            "hack_night_sessions_id"
          ],
          "isUnique": false
        },
        "payload_locked_documents_rels_shelter_id_idx": {
          "name": "payload_locked_documents_rels_shelter_id_idx",
          "columns": [
            "shelter_id"
          ],
          "isUnique": false
        },
        "payload_locked_documents_rels_microgrants_id_idx": {
          "name": "payload_locked_documents_rels_microgrants_id_idx",
          "columns": [
            "microgrants_id"
          ],
          "isUnique": false
        },
        "payload_locked_documents_rels_redirects_id_idx": {
          "name": "payload_locked_documents_rels_redirects_id_idx",
          "columns": [
            "redirects_id"
          ],
          "isUnique": false
        },
        "payload_locked_documents_rels_search_id_idx": {
          "name": "payload_locked_documents_rels_search_id_idx",
          "columns": [
            "search_id"
          ],
          "isUnique": false
        },
        "payload_locked_documents_rels_payload_mcp_api_keys_id_idx": {
          "name": "payload_locked_documents_rels_payload_mcp_api_keys_id_idx",
          "columns": [
            "payload_mcp_api_keys_id"
          ],
          "isUnique": false
        }
      },
      "foreignKeys": {
        "payload_locked_documents_rels_parent_fk": {
          "name": "payload_locked_documents_rels_parent_fk",
          "tableFrom": "payload_locked_documents_rels",
          "tableTo": "payload_locked_documents",
          "columnsFrom": [
            "parent_id"
          ],
          "columnsTo": [
            "id"
          ],
          "onDelete": "cascade",
          "onUpdate": "no action"
        },
        "payload_locked_documents_rels_users_fk": {
          "name": "payload_locked_documents_rels_users_fk",
          "tableFrom": "payload_locked_documents_rels",
          "tableTo": "users",
          "columnsFrom": [
            "users_id"
          ],
          "columnsTo": [
            "id"
          ],
          "onDelete": "cascade",
          "onUpdate": "no action"
        },
        "payload_locked_documents_rels_service_accounts_fk": {
          "name": "payload_locked_documents_rels_service_accounts_fk",
          "tableFrom": "payload_locked_documents_rels",
          "tableTo": "service_accounts",
          "columnsFrom": [
            "service_accounts_id"
          ],
          "columnsTo": [
            "id"
          ],
          "onDelete": "cascade",
          "onUpdate": "no action"
        },
        "payload_locked_documents_rels_media_fk": {
          "name": "payload_locked_documents_rels_media_fk",
          "tableFrom": "payload_locked_documents_rels",
          "tableTo": "media",
          "columnsFrom": [
            "media_id"
          ],
          "columnsTo": [
            "id"
          ],
          "onDelete": "cascade",
          "onUpdate": "no action"
        },
        "payload_locked_documents_rels_events_fk": {
          "name": "payload_locked_documents_rels_events_fk",
          "tableFrom": "payload_locked_documents_rels",
          "tableTo": "events",
          "columnsFrom": [
            "events_id"
          ],
          "columnsTo": [
            "id"
          ],
          "onDelete": "cascade",
          "onUpdate": "no action"
        },
        "payload_locked_documents_rels_emails_fk": {
          "name": "payload_locked_documents_rels_emails_fk",
          "tableFrom": "payload_locked_documents_rels",
          "tableTo": "emails",
          "columnsFrom": [
            "emails_id"
          ],
          "columnsTo": [
            "id"
          ],
          "onDelete": "cascade",
          "onUpdate": "no action"
        },
        "payload_locked_documents_rels_rsvps_fk": {
          "name": "payload_locked_documents_rels_rsvps_fk",
          "tableFrom": "payload_locked_documents_rels",
          "tableTo": "rsvps",
          "columnsFrom": [
            "rsvps_id"
          ],
          "columnsTo": [
            "id"
          ],
          "onDelete": "cascade",
          "onUpdate": "no action"
        },
        "payload_locked_documents_rels_hack_night_sessions_fk": {
          "name": "payload_locked_documents_rels_hack_night_sessions_fk",
          "tableFrom": "payload_locked_documents_rels",
          "tableTo": "hack_night_sessions",
          "columnsFrom": [
            "hack_night_sessions_id"
          ],
          "columnsTo": [
            "id"
          ],
          "onDelete": "cascade",
          "onUpdate": "no action"
        },
        "payload_locked_documents_rels_shelter_fk": {
          "name": "payload_locked_documents_rels_shelter_fk",
          "tableFrom": "payload_locked_documents_rels",
          "tableTo": "shelter",
          "columnsFrom": [
            "shelter_id"
          ],
          "columnsTo": [
            "id"
          ],
          "onDelete": "cascade",
          "onUpdate": "no action"
        },
        "payload_locked_documents_rels_microgrants_fk": {
          "name": "payload_locked_documents_rels_microgrants_fk",
          "tableFrom": "payload_locked_documents_rels",
          "tableTo": "microgrants",
          "columnsFrom": [
            "microgrants_id"
          ],
          "columnsTo": [
            "id"
          ],
          "onDelete": "cascade",
          "onUpdate": "no action"
        },
        "payload_locked_documents_rels_redirects_fk": {
          "name": "payload_locked_documents_rels_redirects_fk",
          "tableFrom": "payload_locked_documents_rels",
          "tableTo": "redirects",
          "columnsFrom": [
            "redirects_id"
          ],
          "columnsTo": [
            "id"
          ],
          "onDelete": "cascade",
          "onUpdate": "no action"
        },
        "payload_locked_documents_rels_search_fk": {
          "name": "payload_locked_documents_rels_search_fk",
          "tableFrom": "payload_locked_documents_rels",
          "tableTo": "search",
          "columnsFrom": [
            "search_id"
          ],
          "columnsTo": [
            "id"
          ],
          "onDelete": "cascade",
          "onUpdate": "no action"
        },
        "payload_locked_documents_rels_payload_mcp_api_keys_fk": {
          "name": "payload_locked_documents_rels_payload_mcp_api_keys_fk",
          "tableFrom": "payload_locked_documents_rels",
          "tableTo": "payload_mcp_api_keys",
          "columnsFrom": [
            "payload_mcp_api_keys_id"
          ],
          "columnsTo": [
            "id"
          ],
          "onDelete": "cascade",
          "onUpdate": "no action"
        }
      },
      "compositePrimaryKeys": {},
      "uniqueConstraints": {},
      "checkConstraints": {}
    },
    "payload_preferences": {
      "name": "payload_preferences",
      "columns": {
        "id": {
          "name": "id",
          "type": "integer",
          "primaryKey": true,
          "notNull": true,
          "autoincrement": false
        },
        "key": {
          "name": "key",
          "type": "text",
          "primaryKey": false,
          "notNull": false,
          "autoincrement": false
        },
        "value": {
          "name": "value",
          "type": "text",
          "primaryKey": false,
          "notNull": false,
          "autoincrement": false
        },
        "updated_at": {
          "name": "updated_at",
          "type": "text",
          "primaryKey": false,
          "notNull": true,
          "autoincrement": false,
          "default": "(strftime('%Y-%m-%dT%H:%M:%fZ', 'now'))"
        },
        "created_at": {
          "name": "created_at",
          "type": "text",
          "primaryKey": false,
          "notNull": true,
          "autoincrement": false,
          "default": "(strftime('%Y-%m-%dT%H:%M:%fZ', 'now'))"
        }
      },
      "indexes": {
        "payload_preferences_key_idx": {
          "name": "payload_preferences_key_idx",
          "columns": [
            "key"
          ],
          "isUnique": false
        },
        "payload_preferences_updated_at_idx": {
          "name": "payload_preferences_updated_at_idx",
          "columns": [
            "updated_at"
          ],
          "isUnique": false
        },
        "payload_preferences_created_at_idx": {
          "name": "payload_preferences_created_at_idx",
          "columns": [
            "created_at"
          ],
          "isUnique": false
        }
      },
      "foreignKeys": {},
      "compositePrimaryKeys": {},
      "uniqueConstraints": {},
      "checkConstraints": {}
    },
    "payload_preferences_rels": {
      "name": "payload_preferences_rels",
      "columns": {
        "id": {
          "name": "id",
          "type": "integer",
          "primaryKey": true,
          "notNull": true,
          "autoincrement": false
        },
        "order": {
          "name": "order",
          "type": "integer",
          "primaryKey": false,
          "notNull": false,
          "autoincrement": false
        },
        "parent_id": {
          "name": "parent_id",
          "type": "integer",
          "primaryKey": false,
          "notNull": true,
          "autoincrement": false
        },
        "path": {
          "name": "path",
          "type": "text",
          "primaryKey": false,
          "notNull": true,
          "autoincrement": false
        },
        "users_id": {
          "name": "users_id",
          "type": "integer",
          "primaryKey": false,
          "notNull": false,
          "autoincrement": false
        },
        "service_accounts_id": {
          "name": "service_accounts_id",
          "type": "integer",
          "primaryKey": false,
          "notNull": false,
          "autoincrement": false
        },
        "payload_mcp_api_keys_id": {
          "name": "payload_mcp_api_keys_id",
          "type": "integer",
          "primaryKey": false,
          "notNull": false,
          "autoincrement": false
        }
      },
      "indexes": {
        "payload_preferences_rels_order_idx": {
          "name": "payload_preferences_rels_order_idx",
          "columns": [
            "order"
          ],
          "isUnique": false
        },
        "payload_preferences_rels_parent_idx": {
          "name": "payload_preferences_rels_parent_idx",
          "columns": [
            "parent_id"
          ],
          "isUnique": false
        },
        "payload_preferences_rels_path_idx": {
          "name": "payload_preferences_rels_path_idx",
          "columns": [
            "path"
          ],
          "isUnique": false
        },
        "payload_preferences_rels_users_id_idx": {
          "name": "payload_preferences_rels_users_id_idx",
          "columns": [
            "users_id"
          ],
          "isUnique": false
        },
        "payload_preferences_rels_service_accounts_id_idx": {
          "name": "payload_preferences_rels_service_accounts_id_idx",
          "columns": [
            "service_accounts_id"
          ],
          "isUnique": false
        },
        "payload_preferences_rels_payload_mcp_api_keys_id_idx": {
          "name": "payload_preferences_rels_payload_mcp_api_keys_id_idx",
          "columns": [
            "payload_mcp_api_keys_id"
          ],
          "isUnique": false
        }
      },
      "foreignKeys": {
        "payload_preferences_rels_parent_fk": {
          "name": "payload_preferences_rels_parent_fk",
          "tableFrom": "payload_preferences_rels",
          "tableTo": "payload_preferences",
          "columnsFrom": [
            "parent_id"
          ],
          "columnsTo": [
            "id"
          ],
          "onDelete": "cascade",
          "onUpdate": "no action"
        },
        "payload_preferences_rels_users_fk": {
          "name": "payload_preferences_rels_users_fk",
          "tableFrom": "payload_preferences_rels",
          "tableTo": "users",
          "columnsFrom": [
            "users_id"
          ],
          "columnsTo": [
            "id"
          ],
          "onDelete": "cascade",
          "onUpdate": "no action"
        },
        "payload_preferences_rels_service_accounts_fk": {
          "name": "payload_preferences_rels_service_accounts_fk",
          "tableFrom": "payload_preferences_rels",
          "tableTo": "service_accounts",
          "columnsFrom": [
            "service_accounts_id"
          ],
          "columnsTo": [
            "id"
          ],
          "onDelete": "cascade",
          "onUpdate": "no action"
        },
        "payload_preferences_rels_payload_mcp_api_keys_fk": {
          "name": "payload_preferences_rels_payload_mcp_api_keys_fk",
          "tableFrom": "payload_preferences_rels",
          "tableTo": "payload_mcp_api_keys",
          "columnsFrom": [
            "payload_mcp_api_keys_id"
          ],
          "columnsTo": [
            "id"
          ],
          "onDelete": "cascade",
          "onUpdate": "no action"
        }
      },
      "compositePrimaryKeys": {},
      "uniqueConstraints": {},
      "checkConstraints": {}
    },
    "payload_migrations": {
      "name": "payload_migrations",
      "columns": {
        "id": {
          "name": "id",
          "type": "integer",
          "primaryKey": true,
          "notNull": true,
          "autoincrement": false
        },
        "name": {
          "name": "name",
          "type": "text",
          "primaryKey": false,
          "notNull": false,
          "autoincrement": false
        },
        "batch": {
          "name": "batch",
          "type": "numeric",
          "primaryKey": false,
          "notNull": false,
          "autoincrement": false
        },
        "updated_at": {
          "name": "updated_at",
          "type": "text",
          "primaryKey": false,
          "notNull": true,
          "autoincrement": false,
          "default": "(strftime('%Y-%m-%dT%H:%M:%fZ', 'now'))"
        },
        "created_at": {
          "name": "created_at",
          "type": "text",
          "primaryKey": false,
          "notNull": true,
          "autoincrement": false,
          "default": "(strftime('%Y-%m-%dT%H:%M:%fZ', 'now'))"
        }
      },
      "indexes": {
        "payload_migrations_updated_at_idx": {
          "name": "payload_migrations_updated_at_idx",
          "columns": [
            "updated_at"
          ],
          "isUnique": false
        },
        "payload_migrations_created_at_idx": {
          "name": "payload_migrations_created_at_idx",
          "columns": [
            "created_at"
          ],
          "isUnique": false
        }
      },
      "foreignKeys": {},
      "compositePrimaryKeys": {},
      "uniqueConstraints": {},
      "checkConstraints": {}
    }
  },
  "views": {},
  "enums": {},
  "_meta": {
    "tables": {},
    "columns": {}
  },
  "internal": {
    "indexes": {}
  },
  "id": "be0c2da3-eb43-4d34-a0c9-008290ceffe2",
  "prevId": "00000000-0000-0000-0000-000000000000"
}